pmr_elirobots_driver/__init__.py
pmr_elirobots_driver/client.py
pmr_elirobots_driver/py.typed
pmr_elirobots_driver/server.py
pmr_elirobots_driver-0.0.2.dist-info/METADATA
pmr_elirobots_driver-0.0.2.dist-info/WHEEL
pmr_elirobots_driver-0.0.2.dist-info/RECORD
