Metadata-Version: 2.4
Name: pmr-elirobots-driver
Version: 0.0.2
Summary: 
Author: Felipe Gomes de Melo D'Elia
Author-email: felipegmelo@usp.br
Requires-Python: >=3.10
Classifier: Programming Language :: Python :: 3
Classifier: Programming Language :: Python :: 3.10
Classifier: Programming Language :: Python :: 3.11
Classifier: Programming Language :: Python :: 3.12
Classifier: Programming Language :: Python :: 3.13
Classifier: Programming Language :: Python :: 3.14
Requires-Dist: pmr_elirobots_msgs
Requires-Dist: pmr_elirobots_sdk
Requires-Dist: pyzmq
Requires-Dist: rich
Requires-Dist: tornado
